segmentation_assessment/AUC.py
segmentation_assessment/__init__.py
segmentation_assessment/assessment_with_ground_truth.py
segmentation_assessment/assessment_without_ground_truth.py
segmentation_assessment/calcul_iou.py
segmentation_assessment/calcul_recall_precision.py
segmentation_assessment/function.py
segmentation_assessment/outline_mask.py
segmentation_assessment/outline_mask_color.py
segmentation_assessment/outline_mask_iou.py
segmentation_assessment/percentage_in_out.py
segmentation_assessment/size_distribution.py
tests/__init__.py
tests/test_functions.py
segmentation_assessment-0.10.1.dist-info/METADATA
segmentation_assessment-0.10.1.dist-info/WHEEL
segmentation_assessment-0.10.1.dist-info/entry_points.txt
segmentation_assessment-0.10.1.dist-info/top_level.txt
segmentation_assessment-0.10.1.dist-info/RECORD
