Metadata-Version: 2.2
Name: segmentation_assessment
Version: 0.10.1
Summary: Assessment of the segmentation quality
Author: Gregoire Menard
Author-email: gregoire.menard.72@hotmail.fr
Dynamic: author
Dynamic: author-email
Dynamic: description
Dynamic: description-content-type
Dynamic: summary
